pyking/__init__.py
pyking/docs/__init__.py
pyking/docs/matext.py
pyking/docs/tutext.py
pyking/mat/__init__.py
pyking/mat/creatM.py
pyking/tushare/__init__.py
pyking/tushare/creat.py
pyking/tushare/creatT.py
pyking/tushare/getinfo.py
pyking/tushare/docs/__init__.py
pyking/tushare/docs/tutext.py
pyking-1.1.1.dist-info/LICENSE
pyking-1.1.1.dist-info/METADATA
pyking-1.1.1.dist-info/WHEEL
pyking-1.1.1.dist-info/top_level.txt
pyking-1.1.1.dist-info/RECORD
