Metadata-Version: 2.1
Name: pyking
Version: 1.1.1
Summary: 富含乱七八糟代码的代码包
Home-page: https://github.com/setupdata/pyking
Author: setupdata
Author-email: ran1144639044@gmail.com
License: UNKNOWN
Platform: UNKNOWN
Requires-Dist: requests
